ff_d/ffd.v
module ffd(
    input wire clk,reset,d,
    output reg q
);


always @(posedge clk or posedge reset)begin
    if(reset)
        q <= 0;
    else
        q <= d;
end
endmodule

ff_d/ffd_tb.v
`default_nettype none
`define DUMPSTR(x) `"x.vcd`"
`timescale 100 ns / 10 ns

module ffd_tb();

//-- Simulation time: 1us (10 * 100ns)
parameter DURATION = 1000;

//-- Clock signal. It is not used in this simulation
reg clk = 0;
always #5 clk = ~clk;

//-- Leds port
reg reset;
reg d;
wire q;

//-- Instantiate the unit to test
ffd UUT(.reset(reset),.d(d),.clk(clk),.q(q));


initial begin
    
  //-- File were to store the simulation results
  $dumpfile(`DUMPSTR(`VCD_OUTPUT));
  $dumpvars(0, ffd_tb);
    reset = 0;

    //ingreso
    d = 0;#10
    d = 1; #10


    d = 0;#10
    d = 1; #10
    #100
  $finish;
end

endmodule

ff_d/ffd_tb.vcd
$date
	Fri Jun 20 10:56:08 2025
$end
$version
	Icarus Verilog
$end
$timescale
	1ps
$end
$scope module ffd_tb $end
$var wire 1 ! q $end
$var parameter 32 " DURATION $end
$var reg 1 # clk $end
$var reg 1 $ d $end
$var reg 1 % reset $end
$scope module UUT $end
$var wire 1 # clk $end
$var wire 1 $ d $end
$var wire 1 % reset $end
$var reg 1 ! q $end
$upscope $end
$upscope $end
$enddefinitions $end
$comment Show the parameter values. $end
$dumpall
b1111101000 "
$end
#0
$dumpvars
0%
0$
0#
x!
$end
#500000
0!
1#
#1000000
0#
1$
#1500000
1!
1#
#2000000
0#
0$
#2500000
0!
1#
#3000000
0#
1$
#3500000
1!
1#
