fsm/fsm.v
module fsm #(
    parameter PULSE_WIDTH_S = 10, // duración del pulso de salida (S)
    parameter PULSE_WIDTH_E = 10  // duración del pulso de entrada (E)
)(
    input wire clk,
    input wire rst,
    input wire A,
    input wire B,
    output reg S, // salida de auto
    output reg E  // entrada de auto
);

    // Estados
    localparam S0 = 2'b00,
               S1 = 2'b10,
               S2 = 2'b11,
               S3 = 2'b01;

    reg [1:0] state, next_state;
    reg [1:0] prev_state;

    // Registro de estado y estado previo
    always @(posedge clk or posedge rst) begin
        if (rst) begin
            state <= S0;
            prev_state <= S0;
            S <= 0;
            E <= 0;
        end else begin
            prev_state <= state;
            state <= next_state;

            // Pulsos según transiciones
            if (prev_state == S1 && state == S0)
                E <= 1;
            else
                E <= 0;

            if (prev_state == S3 && state == S0)
                S <= 1;
            else
                S <= 0;
        end
    end

    // Lógica combinacional de transición de estados
    always @(*) begin
        next_state = state;
        case (state)
            S0: begin
                if ({A,B} == 2'b10)
                    next_state = S1;
                else if ({A,B} == 2'b01)
                    next_state = S3;
            end
            S1: begin
                if ({A,B} == 2'b11)
                    next_state = S2;
                else if ({A,B} == 2'b00)
                    next_state = S0;
            end
            S2: begin
                if ({A,B} == 2'b01)
                    next_state = S3;
                else if ({A,B} == 2'b10)
                    next_state = S1;
            end
            S3: begin
                if ({A,B} == 2'b00)
                    next_state = S0;
                else if ({A,B} == 2'b11)
                    next_state = S2;
            end
        endcase
    end

endmodule

fsm/fsm_tb.v
`define DUMPSTR(x) `"x.vcd`"
`timescale 100 ns / 10 ns

module fsm_tb();

    parameter DURATION = 1000;

    reg clk = 0;
    always #5 clk = ~clk; // Período de 100ns

    // Señales de entrada
    reg rst = 1;
    reg A = 0;
    reg B = 0;

    // Salidas
    wire S; // salida auto
    wire E; // entrada auto

    // Instancia de la FSM
    fsm UUT (
        .clk(clk),
        .rst(rst),
        .A(A),
        .B(B),
        .S(S),
        .E(E)
    );

    initial begin
        $dumpfile(`DUMPSTR(`VCD_OUTPUT));
        $dumpvars(0, fsm_tb);

        // Reset
        rst = 1;
        #20;
        rst = 0;
        

        // === Secuencia de entrada de auto ===
        $display(">> INICIO: Ingreso de auto (esperamos E = 1 al final)");

        A = 0; B = 0; #100;
        A = 1; B = 0; #100; // s0 -> s1
        A = 1; B = 1; #100; // s1 -> s2
        A = 0; B = 1; #100; // s2 -> s3
        A = 0; B = 0; #100; // s3 -> s0 => S = 1 (entrada de auto)

        #100;

        // === Secuencia de salida de auto ===
        $display(">> INICIO: Salida de auto (esperamos S = 1 al final)");

        A = 0; B = 0; #100;
        A = 0; B = 1; #100; // s0 -> s3
        A = 1; B = 1; #100; // s3 -> s2
        A = 1; B = 0; #100; // s2 -> s1
        A = 0; B = 0; #100; // s1 -> s0 => E = 1 (salida de auto)

        #100;

        // === Secuencia inválida ===
        $display(">> INICIO: Secuencia inválida (no debe cambiar salidas)");

        A = 0; B = 0; #100;
        A = 1; B = 1; #100;
        A = 0; B = 0; #100;

        #100;

        $display(">> Fin de simulación.");
        $finish;
    end

endmodule

fsm/fsm_tb.vcd
$date
	Thu Jun 26 10:23:19 2025
$end
$version
	Icarus Verilog
$end
$timescale
	1ps
$end
$scope module fsm_tb $end
$var wire 1 ! S $end
$var wire 1 " E $end
$var parameter 32 # DURATION $end
$var reg 1 $ A $end
$var reg 1 % B $end
$var reg 1 & clk $end
$var reg 1 ' rst $end
$scope module UUT $end
$var wire 1 $ A $end
$var wire 1 % B $end
$var wire 1 & clk $end
$var wire 1 ' rst $end
$var parameter 32 ( PULSE_WIDTH_E $end
$var parameter 32 ) PULSE_WIDTH_S $end
$var parameter 2 * S0 $end
$var parameter 2 + S1 $end
$var parameter 2 , S2 $end
$var parameter 2 - S3 $end
$var reg 1 " E $end
$var reg 1 ! S $end
$var reg 2 . next_state [1:0] $end
$var reg 2 / prev_state [1:0] $end
$var reg 2 0 state [1:0] $end
$upscope $end
$upscope $end
$enddefinitions $end
$comment Show the parameter values. $end
$dumpall
b1 -
b11 ,
b10 +
b0 *
b1010 )
b1010 (
b1111101000 #
$end
#0
$dumpvars
b0 0
b0 /
b0 .
1'
0&
0%
0$
0"
0!
$end
#500000
1&
#1000000
0&
#1500000
1&
#2000000
0&
0'
#2500000
1&
#3000000
0&
#3500000
1&
#4000000
0&
#4500000
1&
#5000000
0&
#5500000
1&
#6000000
0&
#6500000
1&
#7000000
0&
#7500000
1&
#8000000
0&
#8500000
1&
#9000000
0&
#9500000
1&
#10000000
0&
#10500000
1&
#11000000
0&
#11500000
1&
#12000000
b10 .
0&
1$
#12500000
b10 0
1&
#13000000
0&
#13500000
b10 /
1&
#14000000
0&
#14500000
1&
#15000000
0&
#15500000
1&
#16000000
0&
#16500000
1&
#17000000
0&
#17500000
1&
#18000000
0&
#18500000
1&
#19000000
0&
#19500000
1&
#20000000
0&
#20500000
1&
#21000000
0&
#21500000
1&
#22000000
b11 .
0&
1%
#22500000
b11 0
1&
#23000000
0&
#23500000
b11 /
1&
#24000000
0&
#24500000
1&
#25000000
0&
#25500000
1&
#26000000
0&
#26500000
1&
#27000000
0&
#27500000
1&
#28000000
0&
#28500000
1&
#29000000
0&
#29500000
1&
#30000000
0&
#30500000
1&
#31000000
0&
#31500000
1&
#32000000
b1 .
0&
0$
#32500000
b1 0
1&
#33000000
0&
#33500000
b1 /
1&
#34000000
0&
#34500000
1&
#35000000
0&
#35500000
1&
#36000000
0&
#36500000
1&
#37000000
0&
#37500000
1&
#38000000
0&
#38500000
1&
#39000000
0&
#39500000
1&
#40000000
0&
#40500000
1&
#41000000
0&
#41500000
1&
#42000000
b0 .
0&
0%
#42500000
b0 0
1&
#43000000
0&
#43500000
1!
b0 /
1&
#44000000
0&
#44500000
0!
1&
