fsm/ff_d.v
module ff_d(
    input wire clk,reset,d,
    output reg q
);


always @(posedge clk)begin
    if(~reset)
        q <= 0;
    else
        q <= d;
end
endmodule

fsm/fsm.v
module fsm(
    input wire a,b,clk,rst,
    output reg sumar,restar
);

wire [1:0] estado_actual;
reg [1:0] estado_siguiente;

ff_d FF0(.clk(clk),.reset(rst),.d(estado_siguiente[0]),.q(estado_actual[0]));
ff_d FF1(.clk(clk),.reset(rst),.d(estado_siguiente[1]),.q(estado_actual[1]));

localparam S1 = 2'b00,
           S2 = 2'b10,
           S3 = 2'b11,
           S4 = 2'b01;


always @(*) begin
    estado_siguiente = estado_actual;
    sumar = 0;
    restar = 0;

    case(estado_actual)
        S1:begin
            if({a,b} == 2'b10)begin
                estado_siguiente <= S2;
            end else if({a,b} == 2'b01)begin
                estado_siguiente <= S4;
            end
        end

        S2:begin
            if({a,b} == 2'b11)begin
                estado_siguiente <= S3;
            end else if({a,b} == 2'b00)begin
                estado_siguiente <= S1;
                restar = 1;
            end
        end

        S3:begin
            if({a,b} == 2'b01)begin
                estado_siguiente <= S4;
            end else if({a,b} == 2'b10)begin
                estado_siguiente <= S2;
            end
        end

        S4:begin
            if({a,b} == 2'b00)begin
                estado_siguiente <= S1;
                sumar = 1;
            end else if({a,b} == 2'b11)begin
                estado_siguiente <= S3;
            end
        end
    endcase 
end

endmodule

fsm/fsm_tb.v
`default_nettype none
`define DUMPSTR(x) `"x.vcd`"
`timescale 100 ns / 10 ns

module fsm_tb();

//-- Simulation time: 1us (10 * 100ns)
parameter DURATION = 1000;

//-- Clock signal. It is not used in this simulation
reg clk = 0;
always #5 clk = ~clk;

//-- Leds port
wire sum_t,res_t;
reg rst = 1;
reg a_t = 0;
reg b_t = 0;  

//-- Instantiate the unit to test
fsm UUT(.rst(rst),.a(a_t),.b(b_t),.clk(clk),.sumar(sum_t),.restar(res_t));
integer i;

initial begin
    
  //-- File were to store the simulation results
  $dumpfile(`DUMPSTR(`VCD_OUTPUT));
  $dumpvars(0, fsm_tb);
    rst = 0;

    rst = 1;

    //ingreso
    a_t = 1; b_t = 0; #10
    a_t = 1; b_t = 1; #10
    a_t = 0; b_t = 1; #10
    a_t = 0; b_t = 0; #10 //sum (+1) 

    #20;

    //salida
    a_t = 0; b_t = 1; #10
    a_t = 1; b_t = 1; #10
    a_t = 1; b_t = 0; #10
    a_t = 0; b_t = 0; #10 //res (-1) 

    #20;

    //salida
    a_t = 0; b_t = 0; #10
    a_t = 1; b_t = 1; #10
    a_t = 0; b_t = 0; #10
    #20;


    #100
  $finish;
end

endmodule

fsm/fsm_tb.vcd
$date
	Fri Jun 20 10:47:34 2025
$end
$version
	Icarus Verilog
$end
$timescale
	1ps
$end
$scope module fsm_tb $end
$var wire 1 ! sum_t $end
$var wire 1 " res_t $end
$var parameter 32 # DURATION $end
$var reg 1 $ a_t $end
$var reg 1 % b_t $end
$var reg 1 & clk $end
$var reg 1 ' rst $end
$scope module UUT $end
$var wire 1 $ a $end
$var wire 1 % b $end
$var wire 1 & clk $end
$var wire 1 ' rst $end
$var wire 2 ( estado_actual [1:0] $end
$var parameter 2 ) S1 $end
$var parameter 2 * S2 $end
$var parameter 2 + S3 $end
$var parameter 2 , S4 $end
$var reg 2 - estado_siguiente [1:0] $end
$var reg 1 " restar $end
$var reg 1 ! sumar $end
$scope module FF0 $end
$var wire 1 & clk $end
$var wire 1 . d $end
$var wire 1 ' reset $end
$var reg 1 / q $end
$upscope $end
$scope module FF1 $end
$var wire 1 & clk $end
$var wire 1 0 d $end
$var wire 1 ' reset $end
$var reg 1 1 q $end
$upscope $end
$upscope $end
$upscope $end
$enddefinitions $end
$comment Show the parameter values. $end
$dumpall
b1 ,
b11 +
b10 *
b0 )
b1111101000 #
$end
#0
$dumpvars
01
10
0/
0.
b10 -
b0 (
1'
0&
0%
1$
0"
0!
$end
#500000
1&
#1000000
00
b0 -
0&
1%
#1500000
1&
#2000000
1.
b1 -
0&
0$
#2500000
1&
#3000000
0.
b0 -
0&
0%
#3500000
1&
#4000000
0&
#4500000
1&
#5000000
0&
#5500000
1&
#6000000
1.
b1 -
0&
1%
#6500000
1&
#7000000
0.
b0 -
0&
1$
#7500000
1&
#8000000
10
b10 -
0&
0%
#8500000
1&
#9000000
00
b0 -
0&
0$
#9500000
1&
#10000000
0&
#10500000
1&
#11000000
0&
#11500000
1&
#12000000
0&
#12500000
1&
#13000000
0&
1%
1$
#13500000
1&
#14000000
0&
0%
0$
