contador/contador.v
module contador(
    input wire clk, reset,sum,res,
    output reg [2:0] count
);

always@(posedge clk, posedge reset)begin
    if(reset)
        count <= 3'b000;
    else begin
        case({sum,res})
            2'b10: if(count < 7) count <= count + 1; //sumar auto
            2'b01: if(count > 0) count <= count - 1; //restar auto
            default: count <= count;
        endcase
    end
end

endmodule

contador/contador_tb.v
`default_nettype none
`define DUMPSTR(x) `"x.vcd`"
`timescale 100 ns / 10 ns

module contador_tb();

//-- Simulation time: 1us (10 * 100ns)
parameter DURATION = 1000;

//-- Clock signal. It is not used in this simulation
reg clk = 0;
always #5 clk = ~clk;

//-- Leds port
wire [2:0] counter_t;
reg rst,sum_t,res_t;

//-- Instantiate the unit to test
contador UUT(.reset(rst), .count(counter_t), .clk(clk), .sum(sum_t), .res(res_t));
integer i;

initial begin
    
  //-- File were to store the simulation results
  $dumpfile(`DUMPSTR(`VCD_OUTPUT));
  $dumpvars(0, contador_tb);
    rst = 1;  
    sum_t = 0;
    res_t = 0;
    #10

    rst = 0;


    //3 pulsos  suma
    sum_t = 1; #10
    res_t = 0; #20
    
    sum_t = 1; #10
    res_t = 0; #20
    
    sum_t = 1; #10
    res_t = 0; #20
    
    sum_t = 0; #10
    res_t = 1; #20
    
    sum_t = 0; #10
    res_t = 1; #20

    

    #100
  $finish;
end

endmodule

contador/contador_tb.vcd
$date
	Fri Jun 20 10:01:21 2025
$end
$version
	Icarus Verilog
$end
$timescale
	1ps
$end
$scope module contador_tb $end
$var wire 3 ! counter_t [2:0] $end
$var parameter 32 " DURATION $end
$var reg 1 # clk $end
$var reg 1 $ res_t $end
$var reg 1 % rst $end
$var reg 1 & sum_t $end
$scope module UUT $end
$var wire 1 # clk $end
$var wire 1 $ res $end
$var wire 1 % reset $end
$var wire 1 & sum $end
$var reg 3 ' count [2:0] $end
$upscope $end
$upscope $end
$enddefinitions $end
$comment Show the parameter values. $end
$dumpall
b1111101000 "
$end
#0
$dumpvars
b0 '
0&
1%
0$
0#
b0 !
$end
#500000
1#
#1000000
0#
1&
0%
#1500000
b1 !
b1 '
1#
#2000000
0#
#2500000
b10 !
b10 '
1#
#3000000
0#
#3500000
b11 !
b11 '
1#
#4000000
0#
#4500000
b100 !
b100 '
1#
#5000000
0#
#5500000
b101 !
b101 '
1#
#6000000
0#
#6500000
b110 !
b110 '
1#
#7000000
0#
#7500000
b111 !
b111 '
1#
#8000000
0#
#8500000
1#
#9000000
0#
#9500000
1#
#10000000
0#
0&
#10500000
1#
#11000000
0#
1$
#11500000
b110 !
b110 '
1#
#12000000
0#
#12500000
b101 !
b101 '
1#
#13000000
0#
#13500000
b100 !
b100 '
1#
#14000000
0#
#14500000
b11 !
b11 '
1#
#15000000
0#
#15500000
b10 !
b10 '
1#
#16000000
0#
#16500000
b1 !
b1 '
1#
#17000000
0#
#17500000
b0 !
b0 '
1#
